edgar/__init__.py
edgar/__main__.py
edgar/cik.py
edgar_py-0.2.0.dist-info/LICENSE
edgar_py-0.2.0.dist-info/METADATA
edgar_py-0.2.0.dist-info/WHEEL
edgar_py-0.2.0.dist-info/top_level.txt
edgar_py-0.2.0.dist-info/RECORD
