Metadata-Version: 2.1
Name: edgar-py
Version: 0.2.0
Summary: Web scraper and API wrapper for the SEC EDGAR tool.
Author-email: Jacob Lee <Jacob.J.Lee@outlook.com>
License: MIT License
Project-URL: homepage, https://github.com/JacobLee23/EDGAR-py
Classifier: Development Status :: 2 - Pre-Alpha
Classifier: License :: OSI Approved :: MIT License
Classifier: Natural Language :: English
Classifier: Operating System :: OS Independent
Classifier: Programming Language :: Python :: 3
Classifier: Programming Language :: Python :: 3.9
Classifier: Programming Language :: Python :: 3.10
Classifier: Programming Language :: Python :: 3.11
Classifier: Topic :: Office/Business :: Financial :: Investment
Requires-Python: >=3.8
License-File: LICENSE
Requires-Dist: beautifulsoup4 (==4.12.2)
Requires-Dist: lxml (==4.9.3)
Requires-Dist: pandas (==2.0.3)
Requires-Dist: pytz (==2023.3)
Requires-Dist: requests (==2.31.0)
Requires-Dist: charset-normalizer (==3.2.0) ; python_full_version >= "3.7.0"
Requires-Dist: tzdata (==2023.3) ; python_version >= "2"
Requires-Dist: python-dateutil (==2.8.2) ; python_version >= "2.7" and python_version not in "3.0, 3.1, 3.2, 3.3"
Requires-Dist: six (==1.16.0) ; python_version >= "2.7" and python_version not in "3.0, 3.1, 3.2, 3.3"
Requires-Dist: numpy (==1.25.1) ; python_version >= "3.10"
Requires-Dist: idna (==3.4) ; python_version >= "3.5"
Requires-Dist: certifi (==2023.7.22) ; python_version >= "3.6"
Requires-Dist: soupsieve (==2.4.1) ; python_version >= "3.7"
Requires-Dist: urllib3 (==2.0.4) ; python_version >= "3.7"
